netbox_plugin_extensions/__init__.py
netbox_plugin_extensions/filtersets.py
netbox_plugin_extensions/models.py
netbox_plugin_extensions/querysets.py
netbox_plugin_extensions/api/__init__.py
netbox_plugin_extensions/api/fields.py
netbox_plugin_extensions/api/serializers.py
netbox_plugin_extensions/api/views.py
netbox_plugin_extensions/forms/__init__.py
netbox_plugin_extensions/forms/fields.py
netbox_plugin_extensions/forms/model.py
netbox_plugin_extensions/tables/__init__.py
netbox_plugin_extensions/tables/columns.py
netbox_plugin_extensions/tables/objectchange.py
netbox_plugin_extensions/templates/netbox_plugin_extensions/buttons/tr_changelog.html
netbox_plugin_extensions/templates/netbox_plugin_extensions/buttons/tr_delete.html
netbox_plugin_extensions/templates/netbox_plugin_extensions/buttons/tr_edit.html
netbox_plugin_extensions/templates/netbox_plugin_extensions/generic/object.html
netbox_plugin_extensions/templates/netbox_plugin_extensions/generic/object_list.html
netbox_plugin_extensions/templates/netbox_plugin_extensions/generic/objectchange_list.html
netbox_plugin_extensions/templates/netbox_plugin_extensions/inc/panels/tags.html
netbox_plugin_extensions/templatetags/__init__.py
netbox_plugin_extensions/templatetags/plugin_buttons.py
netbox_plugin_extensions/templatetags/plugin_helpers.py
netbox_plugin_extensions/views/__init__.py
netbox_plugin_extensions/views/changelog.py
netbox_plugin_extensions/views/generic.py
netbox_plugin_extensions-1.1.1.dist-info/LICENSE
netbox_plugin_extensions-1.1.1.dist-info/METADATA
netbox_plugin_extensions-1.1.1.dist-info/WHEEL
netbox_plugin_extensions-1.1.1.dist-info/top_level.txt
netbox_plugin_extensions-1.1.1.dist-info/RECORD
